dynamic_watershed/__init__.py
dynamic_watershed/dynamic_watershed.py
dynamic_watershed/version.py
dynamic_watershed-1.0.1.dist-info/METADATA
dynamic_watershed-1.0.1.dist-info/RECORD
dynamic_watershed-1.0.1.dist-info/WHEEL
dynamic_watershed-1.0.1.dist-info/top_level.txt
