Metadata-Version: 2.1
Name: dynamic-watershed
Version: 1.0.1
Summary: Post-processing function used in 'Segmentation of
Home-page: https://github.com/PeterJackNaylor/dynamic_watershed.git
Author: Peter Jack Naylor
Author-email: peter.jack.naylor@gmail.com
License: see LICENSE.txt
Platform: UNKNOWN
Classifier: Programming Language :: Python
Classifier: License :: OSI Approved :: MIT License
Classifier: Operating System :: OS Independent
